{
  "name": "Atkinson Hyperlegible",
  "key": "atkinson-hyperlegible",
  "description": "",
  "license": "OFL-1.1",
  "author": "Braille Institute of America",
  "version": "1.0.0",
  "capabilities": {
    "hasStatic": true,
    "hasVariable": false,
    "weightRange": {
      "min": 400,
      "max": 700,
      "available": [
        400,
        400,
        700,
        700
      ],
      "type": "static"
    },
    "styleCount": 2,
    "formats": [
      "woff2"
    ]
  },
  "files": {
    "static": [
      {
        "key": "AtkinsonHyperlegible-Regular",
        "fileName": "AtkinsonHyperlegible-Regular.woff2",
        "format": "woff2",
        "weight": 400,
        "style": "normal",
        "stretch": "normal",
        "fileSize": 23196,
        "fileSizeKB": 23,
        "_links": {
          "download": {
            "href": "https://cdn.jsdelivr.net/gh/hund-press/font-families@v1.6.0/atkinson-hyperlegible/fonts/webfonts/AtkinsonHyperlegible-Regular.woff2"
          }
        }
      },
      {
        "key": "AtkinsonHyperlegible-Italic",
        "fileName": "AtkinsonHyperlegible-Italic.woff2",
        "format": "woff2",
        "weight": 400,
        "style": "italic",
        "stretch": "normal",
        "fileSize": 24908,
        "fileSizeKB": 24,
        "_links": {
          "download": {
            "href": "https://cdn.jsdelivr.net/gh/hund-press/font-families@v1.6.0/atkinson-hyperlegible/fonts/webfonts/AtkinsonHyperlegible-Italic.woff2"
          }
        }
      },
      {
        "key": "AtkinsonHyperlegible-BoldItalic",
        "fileName": "AtkinsonHyperlegible-BoldItalic.woff2",
        "format": "woff2",
        "weight": 700,
        "style": "italic",
        "stretch": "normal",
        "fileSize": 25160,
        "fileSizeKB": 25,
        "_links": {
          "download": {
            "href": "https://cdn.jsdelivr.net/gh/hund-press/font-families@v1.6.0/atkinson-hyperlegible/fonts/webfonts/AtkinsonHyperlegible-BoldItalic.woff2"
          }
        }
      },
      {
        "key": "AtkinsonHyperlegible-Bold",
        "fileName": "AtkinsonHyperlegible-Bold.woff2",
        "format": "woff2",
        "weight": 700,
        "style": "normal",
        "stretch": "normal",
        "fileSize": 23776,
        "fileSizeKB": 23,
        "_links": {
          "download": {
            "href": "https://cdn.jsdelivr.net/gh/hund-press/font-families@v1.6.0/atkinson-hyperlegible/fonts/webfonts/AtkinsonHyperlegible-Bold.woff2"
          }
        }
      }
    ],
    "variable": []
  },
  "metrics": {
    "unitsPerEm": 1000,
    "ascent": 950,
    "descent": -290,
    "capHeight": 668,
    "xHeight": 496,
    "glyphCount": 369,
    "totalFiles": 4,
    "totalSizeKB": 95
  },
  "performance": {
    "fileCount": 4,
    "totalSizeKB": 95,
    "averageSizeKB": 24,
    "smallestFileKB": 23,
    "largestFileKB": 25,
    "averageGlyphCount": 369
  },
  "typography": {
    "openTypeFeatures": [
      "aalt",
      "case",
      "ccmp",
      "frac",
      "kern",
      "locl",
      "mark",
      "mkmk",
      "ordn",
      "pnum",
      "sups",
      "tnum"
    ],
    "hasLigatures": false,
    "hasSmallCaps": false,
    "hasOldStyleFigures": false,
    "hasTabularFigures": true
  },
  "_links": {
    "self": {
      "href": "/api/families/atkinson-hyperlegible.json"
    },
    "index": {
      "href": "/api/families/"
    },
    "root": {
      "href": "/api/"
    },
    "module": {
      "href": "/modules/atkinson-hyperlegible.js"
    },
    "preview": {
      "href": "/fonts/atkinson-hyperlegible/"
    },
    "cdn": {
      "href": "https://cdn.jsdelivr.net/gh/hund-press/font-families@v1.6.0/atkinson-hyperlegible/",
      "templated": false
    }
  }
}